{
  "files": [
    "C:/Users/kosac/PycharmProjects/petro_chart/Files/148R.las"
  ],
  "pads": [
    {
      "log": false,
      "type": "row",
      "line_quantity": "5",
      "charts": [
        {
          "name": "AZIMUT 148R",
          "color": "#1f77b4",
          "type": "fill",
          "borders": [
            4.1323027611,
            150.0,
            353.35998535
          ],
          "min_border": null,
          "max_border": null,
          "borders_color": [
            "#1f77b4",
            "#ff7f0e",
            "#2ca02c"
          ],
          "fill_side": "left"
        },
        {
          "name": "CO_BEFORE_CALIBRATION 148R",
          "color": "#ff7f0e",
          "type": "line",
          "borders": [
            0.9783306122,
            250.0
          ],
          "min_border": "100",
          "max_border": "150",
          "borders_color": [
            "b"
          ],
          "fill_side": "left"
        }
      ]
    }
  ]
}